synbiochem/__init__.py
synbiochem/biochem4j/__init__.py
synbiochem/biochem4j/taxonomy.py
synbiochem/biochem4j/test/__init__.py
synbiochem/biochem4j/test/test_taxonomy.py
synbiochem/optimisation/__init__.py
synbiochem/optimisation/gen_alg.py
synbiochem/optimisation/sim_ann.py
synbiochem/utils/__init__.py
synbiochem/utils/chem_utils.py
synbiochem/utils/dna_utils.py
synbiochem/utils/expand.txt
synbiochem/utils/graph_utils.py
synbiochem/utils/ice_utils.py
synbiochem/utils/io_utils.py
synbiochem/utils/job.py
synbiochem/utils/mut_utils.py
synbiochem/utils/neo4j_utils.py
synbiochem/utils/net_utils.py
synbiochem/utils/normal.txt
synbiochem/utils/plate_utils.py
synbiochem/utils/sbol_utils.py
synbiochem/utils/seq_utils.py
synbiochem/utils/taxonomy_utils.py
synbiochem/utils/thread_utils.py
synbiochem/utils/test/__init__.py
synbiochem/utils/test/test_chem_utils.py
synbiochem/utils/test/test_dna_utils.py
synbiochem/utils/test/test_ice_utils.py
synbiochem/utils/test/test_mut_utils.py
synbiochem/utils/test/test_neo4j_utils.py
synbiochem/utils/test/test_sbol_utils.py
synbiochem/utils/test/test_seq_utils.py
synbiochem_py-0.6.34.dist-info/LICENSE
synbiochem_py-0.6.34.dist-info/METADATA
synbiochem_py-0.6.34.dist-info/WHEEL
synbiochem_py-0.6.34.dist-info/top_level.txt
synbiochem_py-0.6.34.dist-info/RECORD
