Metadata-Version: 2.1
Name: synbiochem-py
Version: 0.6.34
Summary: synbiochem-py: Core python modules for SYNBIOCHEM
Home-page: https://github.com/synbiochem/synbiochem-py
Author: Neil Swainston
Author-email: neil.swainston@liverpool.ac.uk
License: MIT
Keywords: synbio synthetic biology
Platform: UNKNOWN
Classifier: Development Status :: 4 - Beta
Classifier: Intended Audience :: Developers
Classifier: Topic :: Software Development :: Build Tools
Classifier: License :: OSI Approved :: MIT License
Classifier: Programming Language :: Python :: 3.7
Requires-Dist: biopython
Requires-Dist: numpy
Requires-Dist: pandas
Requires-Dist: requests[security]
Requires-Dist: pyopenssl
